ngraph_tensorflow_bridge-0.18.0.data/purelib/ngraph_bridge/LICENSE
ngraph_tensorflow_bridge-0.18.0.data/purelib/ngraph_bridge/__init__.py
ngraph_tensorflow_bridge-0.18.0.data/purelib/ngraph_bridge/libcpu_backend.so
ngraph_tensorflow_bridge-0.18.0.data/purelib/ngraph_bridge/libinterpreter_backend.so
ngraph_tensorflow_bridge-0.18.0.data/purelib/ngraph_bridge/libiomp5.so
ngraph_tensorflow_bridge-0.18.0.data/purelib/ngraph_bridge/libmkldnn.so
ngraph_tensorflow_bridge-0.18.0.data/purelib/ngraph_bridge/libmklml_intel.so
ngraph_tensorflow_bridge-0.18.0.data/purelib/ngraph_bridge/libngraph.so
ngraph_tensorflow_bridge-0.18.0.data/purelib/ngraph_bridge/libngraph_bridge.so
ngraph_tensorflow_bridge-0.18.0.data/purelib/ngraph_bridge/libngraph_test_util.a
ngraph_tensorflow_bridge-0.18.0.data/purelib/ngraph_bridge/libnop_backend.so
ngraph_tensorflow_bridge-0.18.0.data/purelib/ngraph_bridge/libplaidml_backend.so
ngraph_tensorflow_bridge-0.18.0.data/purelib/ngraph_bridge/libtbb.so
ngraph_tensorflow_bridge-0.18.0.data/purelib/ngraph_bridge/libtbb.so.2
ngraph_tensorflow_bridge-0.18.0.data/purelib/ngraph_bridge/include/ngraph_backend_manager.h
ngraph_tensorflow_bridge-0.18.0.data/purelib/ngraph_bridge/include/ngraph_log.h
ngraph_tensorflow_bridge-0.18.0.data/purelib/ngraph_bridge/include/ngraph/assertion.hpp
ngraph_tensorflow_bridge-0.18.0.data/purelib/ngraph_bridge/include/ngraph/axis_set.hpp
ngraph_tensorflow_bridge-0.18.0.data/purelib/ngraph_bridge/include/ngraph/axis_vector.hpp
ngraph_tensorflow_bridge-0.18.0.data/purelib/ngraph_bridge/include/ngraph/check.hpp
ngraph_tensorflow_bridge-0.18.0.data/purelib/ngraph_bridge/include/ngraph/code_writer.hpp
ngraph_tensorflow_bridge-0.18.0.data/purelib/ngraph_bridge/include/ngraph/coordinate.hpp
ngraph_tensorflow_bridge-0.18.0.data/purelib/ngraph_bridge/include/ngraph/coordinate_diff.hpp
ngraph_tensorflow_bridge-0.18.0.data/purelib/ngraph_bridge/include/ngraph/coordinate_transform.hpp
ngraph_tensorflow_bridge-0.18.0.dist-info/METADATA
ngraph_tensorflow_bridge-0.18.0.dist-info/WHEEL
ngraph_tensorflow_bridge-0.18.0.dist-info/top_level.txt
ngraph_tensorflow_bridge-0.18.0.dist-info/RECORD
