Metadata-Version: 2.1
Name: ngraph-tensorflow-bridge
Version: 0.18.0
Summary: Intel nGraph compiler and runtime for TensorFlow
Home-page: https://github.com/tensorflow/ngraph-bridge
Author: Intel Nervana
License: Apache License, Version 2.0
Platform: Ubuntu 16.04
Platform: macOS Sierra
Provides-Extra: plaidml
Requires-Dist: plaidml (>=0.6.3) ; extra == 'plaidml'
